MANIFEST.in
setup.cfg
setup.py
requirements/base.txt
requirements/dev.txt
yapfsm/__init__.py
yapfsm/engine.py
yapfsm/exceptions.py
yapfsm/transition.py
yapfsm.egg-info/PKG-INFO
yapfsm.egg-info/SOURCES.txt
yapfsm.egg-info/dependency_links.txt
yapfsm.egg-info/top_level.txt