Metadata-Version: 1.0
Name: yapfsm
Version: 0.1.5
Summary: Yet Another Python Finite State Machine
Home-page: UNKNOWN
Author: Jacek Bzdak
Author-email: jacek@askesis.pl
License: UNKNOWN
Platform: UNKNOWN
